{
  "fileFormat" : {
    "charsetName" : "UTF-8",
    "fieldsDelimitedBy" : ",",
    "fieldsEnclosedBy" : "\"",
    "linesTerminatedBy" : "\n",
    "numberOfLinesToIgnore" : 1
  },
  "objects" : [ {
    "name" : "ps_all",
    "fullyQualifiedName" : "ps_all",
    "connector" : "SalesforceAnalyticsCloudDatasetLoader",
    "label" : "ps_all",
    "description" : "ps_all",
    "rowLevelSecurityFilter" : null,
    "fields" : [ {
      "name" : "Id",
      "fullyQualifiedName" : "Id",
      "label" : "Id",
      "description" : "Id",
      "type" : "Numeric",
      "precision" : 18,
      "scale" : 0,
      "decimalSeparator" : ".",
      "defaultValue" : "0",
      "format" : null,
      "isSystemField" : false,
      "isUniqueId" : false,
      "isMultiValue" : false,
      "multiValueSeparator" : null,
      "fiscalMonthOffset" : 0,
      "firstDayOfWeek" : -1,
      "isYearEndFiscalYear" : true,
      "canTruncateValue" : true,
      "isSkipped" : false
    }, {
      "name" : "CpuUse",
      "fullyQualifiedName" : "CpuUse",
      "label" : "CpuUse",
      "description" : "CpuUse",
      "type" : "Numeric",
      "precision" : 18,
      "scale" : 0,
      "decimalSeparator" : ".",
      "defaultValue" : "0",
      "format" : null,
      "isSystemField" : false,
      "isUniqueId" : false,
      "isMultiValue" : false,
      "multiValueSeparator" : null,
      "fiscalMonthOffset" : 0,
      "firstDayOfWeek" : -1,
      "isYearEndFiscalYear" : true,
      "canTruncateValue" : true,
      "isSkipped" : false
    }, {
      "name" : "GpuUse",
      "fullyQualifiedName" : "GpuUse",
      "label" : "GpuUse",
      "description" : "GpuUse",
      "type" : "Numeric",
      "precision" : 18,
      "scale" : 0,
      "decimalSeparator" : ".",
      "defaultValue" : "0",
      "format" : null,
      "isSystemField" : false,
      "isUniqueId" : false,
      "isMultiValue" : false,
      "multiValueSeparator" : null,
      "fiscalMonthOffset" : 0,
      "firstDayOfWeek" : -1,
      "isYearEndFiscalYear" : true,
      "canTruncateValue" : true,
      "isSkipped" : false
    }, {
      "name" : "Comments",
      "fullyQualifiedName" : "Comments",
      "label" : "Comments",
      "description" : "Comments",
      "type" : "Text",
      "precision" : 255,
      "scale" : 0,
      "decimalSeparator" : ".",
      "defaultValue" : null,
      "format" : null,
      "isSystemField" : false,
      "isUniqueId" : false,
      "isMultiValue" : false,
      "multiValueSeparator" : null,
      "fiscalMonthOffset" : 0,
      "firstDayOfWeek" : -1,
      "isYearEndFiscalYear" : true,
      "canTruncateValue" : true,
      "isSkipped" : false
    } ]
  } ]
}